transit/__init__.py
transit/class_hash.py
transit/constants.py
transit/decoder.py
transit/helpers.py
transit/read_handlers.py
transit/reader.py
transit/rolling_cache.py
transit/sosjson.py
transit/transit_types.py
transit/write_handlers.py
transit/writer.py
transit_python2-0.8.321.dist-info/LICENSE
transit_python2-0.8.321.dist-info/METADATA
transit_python2-0.8.321.dist-info/WHEEL
transit_python2-0.8.321.dist-info/top_level.txt
transit_python2-0.8.321.dist-info/RECORD
