Metadata-Version: 2.1
Name: transit-python2
Version: 0.8.321
Summary: Transit marshalling for Python
Home-page: https://github.com/3wnbr1/transit-python2
Author: Cognitect, 3wnbr1
License: UNKNOWN
Platform: UNKNOWN
License-File: LICENSE
Requires-Dist: python-dateutil
Requires-Dist: msgpack-python
